<?xml version = '1.0' encoding = 'UTF-8'?>
<Relation class="oracle.dbtools.crest.model.design.logical.Relation" name="associado_dependente" directorySegmentName="seg_0" id="2098BB01-E575-0D4D-19A5-C37D8E1DB226">
<createdBy>p.falcao</createdBy>
<createdTime>2025-05-16 00:21:30 UTC</createdTime>
<ownerDesignName>ProjDB-Clube</ownerDesignName>
<engineerTo>
<item key="82BAB948-1FD5-58E7-20A7-32E930E27CFD" value="true"/>
</engineerTo>
<sourcePk>F71C80C5-2ABD-32EE-75DB-4731C87DB794</sourcePk>
<identifying>false</identifying>
<optionalSource>true</optionalSource>
<optionalTarget>false</optionalTarget>
<sourceCardinality>1</sourceCardinality>
<sourceEntity>C15AE23F-9050-FFF0-7921-0A04FE40D21D</sourceEntity>
<targetCardinalityString>*</targetCardinalityString>
<targetEntity>2D7F44D8-BD61-D945-AD3A-1DF6B273F8DE</targetEntity>
<transferable>true</transferable>
<deleteRule>NO ACTION</deleteRule>
</Relation>